lotr_sdk/__init__.py
lotr_sdk/client.py
lotr_sdk/fps.py
lotr_sdk/http_client.py
lotr_sdk/movie.py
lotr_sdk/quote.py
ejulio_lotr_sdk-1.0.1.dist-info/METADATA
ejulio_lotr_sdk-1.0.1.dist-info/WHEEL
ejulio_lotr_sdk-1.0.1.dist-info/top_level.txt
ejulio_lotr_sdk-1.0.1.dist-info/RECORD
